odoo10_addon_shopinvader_delivery_instruction-10.0.1.0.2-nspkg.pth
odoo/addons/shopinvader_delivery_instruction/__init__.py
odoo/addons/shopinvader_delivery_instruction/__manifest__.py
odoo/addons/shopinvader_delivery_instruction/services/__init__.py
odoo/addons/shopinvader_delivery_instruction/services/abstract_sale.py
odoo/addons/shopinvader_delivery_instruction/services/cart.py
odoo/addons/shopinvader_delivery_instruction/tests/__init__.py
odoo/addons/shopinvader_delivery_instruction/tests/test_sale_order_picking_note.py
odoo10_addon_shopinvader_delivery_instruction-10.0.1.0.2.dist-info/METADATA
odoo10_addon_shopinvader_delivery_instruction-10.0.1.0.2.dist-info/WHEEL
odoo10_addon_shopinvader_delivery_instruction-10.0.1.0.2.dist-info/namespace_packages.txt
odoo10_addon_shopinvader_delivery_instruction-10.0.1.0.2.dist-info/top_level.txt
odoo10_addon_shopinvader_delivery_instruction-10.0.1.0.2.dist-info/RECORD
