Metadata-Version: 2.1
Name: odoo10-addon-shopinvader-delivery-instruction
Version: 10.0.1.0.2
Summary: Shopinvader addons to let user define delivery instructions
Home-page: http://shopinvader.com/
Author: ACSONE SA/NV
License: AGPL-3
Platform: UNKNOWN
Classifier: Programming Language :: Python
Classifier: Framework :: Odoo
Classifier: License :: OSI Approved :: GNU Affero General Public License v3
Requires-Python: ~=2.7
Requires-Dist: odoo10-addon-sale-stock-picking-note
Requires-Dist: odoo10-addon-shopinvader
Requires-Dist: odoo (<10.1dev,>=10.0)
